{"run_number": "1732668249963017", "step_name": "classification_report", "task_id": "6", "attempt_id": 0, "name": "html", "content_type": "gzip+pickle-v2", "type": "metaflow.artifact", "sha": "4b6cc3191bf2092ac3c6b443009a4f1ed4df0eac", "ds_type": "local", "location": ":root:/Users/gabriel/Documents/ML_school/ml.school.opensource/kaggle/.metaflow", "flow_id": "Monitoring", "user_name": "gabriel", "tags": [], "system_tags": ["project_branch:user.gabriel", "metaflow_version:2.12.28", "runtime:dev", "project:weather_report_kaggle", "user:gabriel", "python_version:3.12.0"], "ts_epoch": 1732668273511}